setup.py
messageconnoisseur/__init__.py
messageconnoisseur/common.py
messageconnoisseur/configuration.py
messageconnoisseur/exporting.py
messageconnoisseur/importing.py
messageconnoisseur/scripts.py
messageconnoisseur.egg-info/PKG-INFO
messageconnoisseur.egg-info/SOURCES.txt
messageconnoisseur.egg-info/dependency_links.txt
messageconnoisseur.egg-info/entry_points.txt
messageconnoisseur.egg-info/not-zip-safe
messageconnoisseur.egg-info/top_level.txt