Metadata-Version: 1.0
Name: messageconnoisseur
Version: 0.2.0
Summary: Message log parser and message processor
Home-page: http://github.com/spasticVerbalizer/messageconnoisseur
Author: Maarten van den Berg
Author-email: schoenveter123+git@gmail.com
License: MIT
Platform: UNKNOWN
